apieasy/__init__.py
apieasy/cli.py
apieasy/decorators.py
apieasy/http_utils.py
apieasy/router.py
apieasy/server.py
apieasy-0.1.0.dist-info/licenses/LICENSE
apieasy-0.1.0.dist-info/METADATA
apieasy-0.1.0.dist-info/WHEEL
apieasy-0.1.0.dist-info/entry_points.txt
apieasy-0.1.0.dist-info/top_level.txt
apieasy-0.1.0.dist-info/RECORD
