Metadata-Version: 2.4
Name: apieasy
Version: 0.1.0
Summary: A minimal REST API framework using simple Python function decorators.
Author-email: Sai Sarthak Sadangi <your_email@example.com>
License: MIT
Project-URL: Homepage, https://github.com/sai-AIstacker/apieasy
Project-URL: Source, https://github.com/sai-AIstacker/apieasy
Project-URL: Issues, https://github.com/sai-AIstacker/apieasy/issues
Requires-Python: >=3.8
License-File: LICENSE
Dynamic: license-file
